codescream/__init__.py
codescream/scream1.wav
codescream-1.0.0.dist-info/METADATA
codescream-1.0.0.dist-info/WHEEL
codescream-1.0.0.dist-info/top_level.txt
codescream-1.0.0.dist-info/RECORD
