Metadata-Version: 2.1
Name: codescream
Version: 1.0.0
Summary: Read the latest Real Python tutorials
Home-page: https://github.com/irth/codescream
Author: Wojciech ~irth Kwolek
Author-email: me@irth.pl
License: MIT
Platform: UNKNOWN
Classifier: License :: OSI Approved :: MIT License
Classifier: Programming Language :: Python :: 3
Classifier: Programming Language :: Python :: 3.7
Requires-Dist: playsound
